pactown_guard/__init__.py
pactown_guard/cli.py
pactown_guard/pactowncom.py
pactown_guard/venv/lib/python3.13/site-packages/pip/__init__.py
pactown_guard/venv/lib/python3.13/site-packages/pip/__main__.py
pactown_guard/venv/lib/python3.13/site-packages/pip/__pip-runner__.py
pactown_guard/venv/lib/python3.13/site-packages/pip/_internal/__init__.py
pactown_guard/venv/lib/python3.13/site-packages/pip/_internal/build_env.py
pactown_guard/venv/lib/python3.13/site-packages/pip/_internal/cache.py
pactown_guard/venv/lib/python3.13/site-packages/pip/_internal/configuration.py
pactown_guard/venv/lib/python3.13/site-packages/pip/_internal/exceptions.py
pactown_guard/venv/lib/python3.13/site-packages/pip/_internal/main.py
pactown_guard/venv/lib/python3.13/site-packages/pip/_internal/pyproject.py
pactown_guard/venv/lib/python3.13/site-packages/pip/_internal/self_outdated_check.py
pactown_guard/venv/lib/python3.13/site-packages/pip/_internal/wheel_builder.py
pactown_guard/venv/lib/python3.13/site-packages/pip/_internal/cli/__init__.py
pactown_guard/venv/lib/python3.13/site-packages/pip/_internal/cli/autocompletion.py
pactown_guard/venv/lib/python3.13/site-packages/pip/_internal/cli/base_command.py
pactown_guard/venv/lib/python3.13/site-packages/pip/_internal/cli/cmdoptions.py
pactown_guard/venv/lib/python3.13/site-packages/pip/_internal/cli/command_context.py
pactown_guard/venv/lib/python3.13/site-packages/pip/_internal/cli/index_command.py
pactown_guard/venv/lib/python3.13/site-packages/pip/_internal/cli/main.py
pactown_guard/venv/lib/python3.13/site-packages/pip/_internal/cli/main_parser.py
pactown_guard/venv/lib/python3.13/site-packages/pip/_internal/cli/parser.py
pactown_guard/venv/lib/python3.13/site-packages/pip/_internal/cli/progress_bars.py
pactown_guard/venv/lib/python3.13/site-packages/pip/_internal/cli/req_command.py
pactown_guard/venv/lib/python3.13/site-packages/pip/_internal/cli/spinners.py
pactown_guard-0.1.6.dist-info/METADATA
pactown_guard-0.1.6.dist-info/WHEEL
pactown_guard-0.1.6.dist-info/entry_points.txt
pactown_guard-0.1.6.dist-info/top_level.txt
pactown_guard-0.1.6.dist-info/RECORD
