Metadata-Version: 2.4
Name: pactown-guard
Version: 0.1.6
Summary: Interactive diagnostics/triage guard for Pactown on VPS
License: Proprietary
Requires-Python: >=3.10
